LICENSE
README.md
setup.py
datadictpy/__init__.py
datadictpy/datadictpy.py
datadictpy.egg-info/PKG-INFO
datadictpy.egg-info/SOURCES.txt
datadictpy.egg-info/dependency_links.txt
datadictpy.egg-info/top_level.txt