Metadata-Version: 2.4
Name: datadictpy
Version: 0.2
Summary: DBMS NoSQL based on python dictionaries and dictionary lists
Author: Heitor Fernandes Silva
Author-email: heitor.ceab@gmail.com
License: MIT License
Keywords: python database
License-File: LICENSE
Dynamic: author
Dynamic: author-email
Dynamic: description
Dynamic: description-content-type
Dynamic: keywords
Dynamic: license
Dynamic: license-file
Dynamic: summary
